merchant001_sdk/__about__.py
merchant001_sdk/__init__.py
merchant001_sdk/__main__.py
merchant001_sdk/cli/__init__.py
merchant001_sdk/cli/entrypoint.py
merchant001_sdk/cli/groups/__init__.py
merchant001_sdk/client/__init__.py
merchant001_sdk/client/base.py
merchant001_sdk/client/client.py
merchant001_sdk/core/__init__.py
merchant001_sdk/core/data/__init__.py
merchant001_sdk/core/data/enum/__init__.py
merchant001_sdk/core/data/enum/base.py
merchant001_sdk/core/data/schemas/__init__.py
merchant001_sdk/core/data/schemas/base.py
merchant001_sdk/core/data/schemas/responses/__init__.py
merchant001_sdk/core/data/schemas/responses/error.py
merchant001_sdk/core/data/schemas/responses/healthcheck.py
merchant001_sdk/core/data/schemas/responses/payment_method.py
merchant001_sdk/core/data/schemas/responses/rate.py
merchant001_sdk/core/data/schemas/responses/raw.py
merchant001_sdk/core/data/schemas/responses/status_stub.py
merchant001_sdk/core/data/schemas/responses/transaction.py
merchant001_sdk/core/errors/__init__.py
merchant001_sdk/core/errors/base.py
merchant001_sdk/core/errors/client_closed.py
merchant001_sdk/core/errors/http_error.py
merchant001_sdk/core/errors/internal_code_error.py
merchant001_sdk-0.0.21.dist-info/entry_points.txt
merchant001_sdk-0.0.21.dist-info/WHEEL
merchant001_sdk-0.0.21.dist-info/METADATA
merchant001_sdk-0.0.21.dist-info/license_files/LICENSE
merchant001_sdk-0.0.21.dist-info/RECORD
