Metadata-Version: 2.1
Name: merchant001_sdk
Version: 0.0.21
Keywords: CLI,client,convertation,crypto,usdt
Author-email: Alexander Lavrov <alexander.lavrov@elastoo.com>
Requires-Python: >=3.10,<=3.12
Classifier: Development Status :: 5 - Production/Stable
Classifier: Environment :: Other Environment
Classifier: Intended Audience :: Developers
Classifier: Intended Audience :: Science/Research
Classifier: License :: OSI Approved :: MIT License
Classifier: Operating System :: OS Independent
Classifier: Programming Language :: Python
Classifier: Topic :: Software Development :: Libraries :: Python Modules
Requires-Dist: httpx>=0.24.0
Provides-Extra: cli
Requires-Dist: cliar>=1.3.5; extra == "cli"
Project-URL: documentation, https://merchant001_sdk.readthedocs.io
Project-URL: repository, https://github.com/Elastoo-Team/merchant001_sdk
